CHANGELOG.md
LICENSE
MANIFEST.in
README.md
interceptor.py
setup.py
SimpleInterceptor.egg-info/PKG-INFO
SimpleInterceptor.egg-info/SOURCES.txt
SimpleInterceptor.egg-info/dependency_links.txt
SimpleInterceptor.egg-info/entry_points.txt
SimpleInterceptor.egg-info/requires.txt
SimpleInterceptor.egg-info/top_level.txt
example/__init__.py
example/intercept.jpg
example/non-intercept.jpg
example/ansible_lint/pycallgraph.jpg
example/ansible_lint/wxPython-src-3.0.2.0/samples/image/cmyk.jpg
example/ansible_lint/wxPython-src-3.0.2.0/samples/image/horse.jpg
example/ansible_lint/wxPython-src-3.0.2.0/src/png/pngbar.jpg
example/ansible_lint/wxPython-src-3.0.2.0/src/tiff/html/images/bali.jpg
example/ansible_lint/wxPython-src-3.0.2.0/src/tiff/html/images/cover.jpg
example/ansible_lint/wxPython-src-3.0.2.0/src/tiff/html/images/jello.jpg
example/ansible_lint/wxPython-src-3.0.2.0/src/tiff/html/images/quad.jpg
example/ansible_lint/wxPython-src-3.0.2.0/src/tiff/html/images/smallliz.jpg
example/ansible_lint/wxPython-src-3.0.2.0/utils/emulator/docs/screen01.jpg
example/ansible_lint/wxPython-src-3.0.2.0/utils/emulator/docs/screen02.jpg
example/ansible_lint/wxPython-src-3.0.2.0/utils/emulator/src/bluegradient.jpg
example/ansible_lint/wxPython-src-3.0.2.0/utils/emulator/src/ipaq01.jpg
example/ansible_lint/wxPython-src-3.0.2.0/wxPython/demo/bitmaps/image.jpg
example/ansible_lint/wxPython-src-3.0.2.0/wxPython/demo/bmp_source/robin.jpg
example/ansible_lint/wxPython-src-3.0.2.0/wxPython/samples/wxPIA_book/Chapter-01/wxPython.jpg
example/ansible_lint/wxPython-src-3.0.2.0/wxPython/samples/wxPIA_book/Chapter-12/image.jpg
example/lint_pbook/README.md
example/lint_pbook/__init__.py
example/lint_pbook/advanced_lint.py
example/lint_pbook/composite_queue.py
example/lint_pbook/lint.py
example/lint_pbook/linter_output.jpg
example/lint_pbook/playbook.yml
example/lint_pbook/group_vars/ips
example/print_output/__init__.py
example/print_output/advice.py
example/print_output/primary_concern.py
test/__init__.py
test/advanced_advices.py
test/advanced_primary_concerns.py
test/advices.py
test/primary_concerns.py
test/test_interceptor.py