Metadata-Version: 1.1
Name: SimpleInterceptor
Version: 0.1
Summary: Simple interceptor related to concepts of AOP
Home-page: https://github.com/host-anshu/simpleInterceptor
Author: Anshu Choubey
Author-email: anshu.choubey@imaginea.com
License: MIT
Keywords: interceptor aop
Platform: UNKNOWN
Classifier: Development Status :: 3 - Alpha
Classifier: Intended Audience :: Developers
Classifier: Topic :: Software Development :: Libraries :: Python Modules
Classifier: License :: OSI Approved :: MIT License
Classifier: Programming Language :: Python :: 2
Classifier: Programming Language :: Python :: 2.6
Classifier: Programming Language :: Python :: 2.7
